README.rst
flags.py
setup.py
pyflags.egg-info/PKG-INFO
pyflags.egg-info/SOURCES.txt
pyflags.egg-info/dependency_links.txt
pyflags.egg-info/top_level.txt