Metadata-Version: 1.1
Name: pyflags
Version: 0.1
Summary: A simple, common-sense, single-letter command-line parser
Home-page: UNKNOWN
Author: Ryan Gonzalez
Author-email: UNKNOWN
License: UNKNOWN
Platform: UNKNOWN
Classifier: License :: OSI Approved :: MIT License
